msrdm/__init__.py
msrdm-0.0.2.dist-info/LICENSE
msrdm-0.0.2.dist-info/METADATA
msrdm-0.0.2.dist-info/WHEEL
msrdm-0.0.2.dist-info/top_level.txt
msrdm-0.0.2.dist-info/RECORD
