Metadata-Version: 2.1
Name: msrdm
Version: 0.0.2
Summary: Multi-Stage Robust Decision Making
Home-page: https://github.com/shunichironomura/msrdm
Author: Shunichiro Nomura
Author-email: nomura@space.t.u-tokyo.ac.jp
License: BSD 3-Clause
Download-URL: https://github.com/shunichironomura/msrdm/archive/v0.0.2.tar.gz
Platform: UNKNOWN
Classifier: Development Status :: 1 - Planning
Classifier: Intended Audience :: Science/Research
Classifier: License :: OSI Approved :: BSD License
Classifier: Programming Language :: Python :: 3
Classifier: Programming Language :: Python :: 3.8
Requires-Dist: numpy
Requires-Dist: pandas
